{
  "process": "cnc_3axis",
  "material": "",
  "quantity": 1,
  "unit_cost_usd": 133.21,
  "breakdown": {
    "material_usd": 0.12,
    "machining_usd": 35.67,
    "setup_usd": 75.0,
    "finishing_usd": 0.21,
    "margin_usd": 22.2
  },
  "lead_time_days": 4,
  "geometry": {
    "bbox_mm": [
      50.0,
      30.0,
      10.0
    ],
    "volume_cm3": 5.4872,
    "stock_volume_cm3": 15.0,
    "material_removal_pct": 63.4,
    "surface_area_cm2": 42.8483,
    "face_count": 12
  },
  "optimizations": [
    "Simplify the design by removing unnecessary features to reduce machining time ($5 savings)",
    "Optimize toolpath generation for efficient material removal ($10 savings)"
  ],
  "confidence": "high",
  "risks": [
    "Material removal is relatively low at 63%, which may indicate a part with many features or small details that could increase machining time."
  ]
}