{
  "process": "cnc_3axis",
  "material": "steel_mild",
  "quantity": 1,
  "unit_cost_usd": 96.49,
  "breakdown": {
    "material_usd": 0.07,
    "machining_usd": 5.27,
    "setup_usd": 75.0,
    "finishing_usd": 0.07,
    "margin_usd": 16.08
  },
  "lead_time_days": 5,
  "geometry": {
    "bbox_mm": [
      30.0,
      12.0,
      8.0
    ],
    "volume_cm3": 1.7858,
    "stock_volume_cm3": 2.88,
    "material_removal_pct": 38.0,
    "surface_area_cm2": 13.5308,
    "face_count": 23
  },
  "optimizations": [
    "Reduce wall thickness in areas where possible ($1.50 savings)",
    "Simplify part geometry by eliminating unnecessary features or consolidating pockets ($2.00 savings)",
    "Consider using a more efficient machining strategy (e.g., 4-axis) if the part's complexity warrants it ($3.00 savings)"
  ],
  "confidence": "medium",
  "risks": [
    "Deep pockets may require specialized tooling or longer machining time.",
    "Thin walls (8 mm) could lead to vibration issues during machining, affecting surface finish and potentially requiring additional setup."
  ]
}